README.md
setup.py
cha_dist/Binomialdistribution.py
cha_dist/Generaldistribution.py
cha_dist/Guassiandistribution.py
cha_dist/__init__.py
cha_dist.egg-info/PKG-INFO
cha_dist.egg-info/SOURCES.txt
cha_dist.egg-info/dependency_links.txt
cha_dist.egg-info/not-zip-safe
cha_dist.egg-info/top_level.txt