Metadata-Version: 2.1
Name: cha-dist
Version: 0.4
Summary: Gaussian distributions
Home-page: UNKNOWN
Author: Nagesh Singh Chauhan
Author-email: nageshsinghc4@gmail.com
License: UNKNOWN
Platform: UNKNOWN
